picsellia_annotations/__init__.py
picsellia_annotations/coco.py
picsellia_annotations/exceptions.py
picsellia_annotations/utils.py
picsellia_annotations/video_coco.py
picsellia_annotations/voc.py
picsellia_annotations-0.12.1.dist-info/LICENSE
picsellia_annotations-0.12.1.dist-info/METADATA
picsellia_annotations-0.12.1.dist-info/WHEEL
picsellia_annotations-0.12.1.dist-info/RECORD
