Metadata-Version: 2.3
Name: picsellia-annotations
Version: 0.12.1
Summary: Package with pydantic schemas of COCO files and VOC File and some utils to read those annotations files
Author: picsellia
Requires-Python: >=3.10
Classifier: Programming Language :: Python :: 3
Classifier: Programming Language :: Python :: 3.10
Classifier: Programming Language :: Python :: 3.11
Classifier: Programming Language :: Python :: 3.12
Classifier: Programming Language :: Python :: 3.13
Requires-Dist: pydantic (>=2.0.0,<3.0.0)
Requires-Dist: xmltodict (>=1.0.0,<2.0.0)
